courselevels/version.py
courselevels/static/courselevels.yaml
courselevels/static/index.js
nb_courselevels-0.5.4.data/data/etc/jupyter/nbconfig/notebook.d/nb-courselevels.json
nb_courselevels-0.5.4.data/data/share/jupyter/nbextensions/courselevels/courselevels.yaml
nb_courselevels-0.5.4.data/data/share/jupyter/nbextensions/courselevels/index.js
nb_courselevels-0.5.4.dist-info/LICENSE
nb_courselevels-0.5.4.dist-info/METADATA
nb_courselevels-0.5.4.dist-info/WHEEL
nb_courselevels-0.5.4.dist-info/top_level.txt
nb_courselevels-0.5.4.dist-info/RECORD
