Metadata-Version: 2.1
Name: nb-courselevels
Version: 0.5.4
Summary: Jupyter nbextension to outline 3 course levels through colors
Home-page: UNKNOWN
Author: Thierry Parmentelat
Author-email: thierry.parmentelat@inria.fr
License: UNKNOWN
Project-URL: source, https://github.com/parmentelat/nb-courselevels
Platform: UNKNOWN
Requires-Dist: notebook
Requires-Dist: jupyter-nbextensions-configurator
